[
    {
        "source": "France Travail",
        "job_title": "Architecte Data IA Cloud H/F",
        "contract_type": "CDI",
        "salary": null,
        "company": "ENOVA CONSULTING ",
        "location": "Alpes-Maritimes",
        "remote": null,
        "experience": "Expérience exigée",
        "education_level": null,
        "publication_date": "2025-02-03",
        "company_data": {
            "sector": null,
            "company_size": "Fondé à Genève en 2018, Enova Group offre des services informatiques en Suisse, au Luxembourg, en France et prochainement à Monaco. Spécialisé en conseil stratégique numérique, performance opérationnelle et technologies de l'information. Nous nous concentrons sur les compétences IT les plus recherchées et la gestion complète de projets.\n\nNotre expertise holistique nous permet d'accompagner efficacement nos clients dans leurs projets, en cultivant des partenariats solide...",
            "creation_date": null,
            "address": null,
            "average_age_of_employees": null,
            "turnover_in_millions": null,
            "proportion_female": null,
            "proportion_male": null
        },
        "link": "https://candidat.francetravail.fr/offres/recherche/detail/1657379",
        "description": "POSTE : Architecte Data IA Cloud H/F\nDESCRIPTION : Rejoignez un acteur majeur du secteur numérique, où l'innovation et la technologie sont au coeur des projets. Dans un environnement stimulant et collaboratif, vous serez un élément clé pour accompagner nos clients dans leurs projets de transformation numérique, en mettant à profit vos compétences en cloud computing, data et intelligence artificielle.\n\nBasé à Sophia-Antipolis, vous intégrerez une équipe dynamique spécialisée dans la conception et la mise en oeuvre de solutions à forte valeur ajoutée, à l'avant-garde des technologies Cloud et IA.\n\nEn tant qu'Architecte Data IA/Cloud, vous serez responsable de la conception, du déploiement et de l'optimisation des architectures data et IA sur les principales plateformes cloud (AWS, GCP). Votre rôle sera stratégique pour garantir l'efficacité, la scalabilité et la sécurité des solutions proposées.\n\nVos principales responsabilités :\n\n1. Conception et architecture :\n- Concevoir des architectures data innovantes, évolutives et sécurisées sur les plateformes AWS et GCP.\n- Développer et intégrer des solutions IA adaptées aux besoins métiers, en tirant parti des outils natifs des clouds publics.\n- Superviser et coordonner les phases de design technique, en collaboration avec les équipes projet.\n\n2. Mise en oeuvre des solutions :\n- Assurer le déploiement des pipelines data et des infrastructures Cloud nécessaires aux projets IA.\n- Garantir une intégration optimale entre les environnements Cloud et les systèmes existants.\n- Identifier les meilleures pratiques pour automatiser et industrialiser les processus (CI/CD, Infrastructure as Code).\n\n3. Conseil et expertise technique :\n- Accompagner les équipes dans le choix des technologies et des outils Cloud et Data.\n- Être force de proposition sur les solutions technologiques pour répondre aux enjeux stratégiques des clients.\n- Veiller à la veille technologique sur les domaines IA et Cloud pour anticiper les évolutions du marché.\n- Rejoignez une équipe à taille humaine, au coeur de Sophia-Antipolis, dans l'un des pôles technologiques les plus dynamiques d'Europe.\n- Bénéficiez d'un environnement stimulant, à l'avant-garde des technologies Cloud et IA.\n- Participez à des projets d'envergure avec des clients de renom.\n- Évoluez dans un cadre professionnel où l'expertise et la montée en compétences sont valorisées.\n- 2 000€ de formation annuelle offerte\nPROFIL : - Solide expertise en Cloud Computing avec une maîtrise des plateformes AWS et GCP (certifications appréciées).\n- Connaissance approfondie des technologies Big Data (Spark, Hadoop, BigQuery, Redshift, etc.).\n- Expérience significative dans le domaine de l'IA (développement de modèles, MLOPS, TensorFlow, PyTorch, etc.).\n- Compétences en automatisation et en outils DEVOPS (Terraform, Kubernetes, CI/CD).\n- Bonne compréhension des problématiques de sécurité et de gestion des données.\n- Vous êtes curieux(se) et aimez explorer de nouvelles technologies.\n- Polyvalent(e) et orienté(e) solution, vous savez vous adapter à des contextes variés.\n- Excellent(e) communicant(e), vous savez vulgariser des sujets techniques complexes auprès de publics non-techniques.\n- Vous aimez travailler en équipe et avez à coeur de transmettre vos connaissances. Expérience\n- 5 ans minimum d'expérience sur des projets Data/Cloud, idéalement dans un environnement agile.",
        "job_reference": "1657379",
        "job": "data architect",
        "skills": {
            "BigData": [
                "Hadoop",
                "Spark"
            ],
            "MachineLearning": [
                "PyTorch",
                "TensorFlow"
            ],
            "CloudComputing": [
                "GCP",
                "AWS"
            ],
            "DBMS": [
                "BigQuery"
            ],
            "Automation": [
                "Kubernetes"
            ],
            "InfrastructureAsCode": [
                "Terraform"
            ],
            "Containers": [
                "Kubernetes"
            ],
            "Other": [
                "DevOps",
                "CI/CD",
                "Big Data",
                "Cloud"
            ],
            "EnSoftSkils": [
                "Collaboration"
            ]
        }
    }
]